simple_repository_server/__init__.py
simple_repository_server/__main__.py
simple_repository_server/_http_response_iterator.py
simple_repository_server/_version.py
simple_repository_server/py.typed
simple_repository_server/utils.py
simple_repository_server/routers/__init__.py
simple_repository_server/routers/simple.py
simple_repository_server/tests/__init__.py
simple_repository_server/tests/test__http_response_iterator.py
simple_repository_server/tests/test_netrc_auth.py
simple_repository_server/tests/api/__init__.py
simple_repository_server/tests/api/test_simple_router.py
simple_repository_server/tests/integration/__init__.py
simple_repository_server/tests/integration/test_repo_dependency_injection.py
simple_repository_server/tests/unit/__init__.py
simple_repository_server/tests/unit/test_utils.py
simple_repository_server-0.10.0.dist-info/licenses/LICENSE
simple_repository_server-0.10.0.dist-info/METADATA
simple_repository_server-0.10.0.dist-info/WHEEL
simple_repository_server-0.10.0.dist-info/entry_points.txt
simple_repository_server-0.10.0.dist-info/top_level.txt
simple_repository_server-0.10.0.dist-info/RECORD
