Metadata-Version: 2.4
Name: simple-repository-server
Version: 0.10.0
Summary: A tool for running a PEP-503 simple Python package repository, including features such as dist metadata (PEP-658) and JSON API (PEP-691)
Author: Phil Elson, Ivan Sinkarenko, Francesco Iannaccone, Wouter Koorn
Project-URL: Homepage, https://github.com/simple-repository/simple-repository-server
Classifier: Development Status :: 4 - Beta
Classifier: Programming Language :: Python :: 3
Classifier: Framework :: FastAPI
Classifier: Operating System :: OS Independent
Classifier: Typing :: Typed
Requires-Python: >=3.11
License-File: LICENSE
Requires-Dist: httpx
Requires-Dist: fastapi>=0.100.0
Requires-Dist: packaging
Requires-Dist: uvicorn[standard]
Requires-Dist: simple-repository>=0.10.0
Provides-Extra: test
Requires-Dist: pytest; extra == "test"
Requires-Dist: pytest_asyncio; extra == "test"
Requires-Dist: pytest_httpx; extra == "test"
Requires-Dist: starlette>=0.26.1; extra == "test"
Requires-Dist: pytest_httpserver; extra == "test"
Provides-Extra: dev
Requires-Dist: simple-repository-server[test]; extra == "dev"
Dynamic: license-file
